linuxbackup/__init__.py
linuxbackup/linuxbackup.py
linuxbackup-0.0.1.dist-info/METADATA
linuxbackup-0.0.1.dist-info/WHEEL
linuxbackup-0.0.1.dist-info/top_level.txt
linuxbackup-0.0.1.dist-info/RECORD
