Metadata-Version: 2.1
Name: linuxbackup
Version: 0.0.1
Summary: Backup and restore for linux
Home-page: https://github.com/pypa/sampleproject
Author: Tianyi Chen
Author-email: 
License: UNKNOWN
Platform: UNKNOWN
Classifier: Programming Language :: Python :: 3
Classifier: License :: Other/Proprietary License
Classifier: Operating System :: POSIX :: Linux
